crawlfrontier/_version.py
crawlfrontier/__init__.py
crawlfrontier/exceptions.py
crawlfrontier/core/components.py
crawlfrontier/core/models.py
crawlfrontier/core/manager.py
crawlfrontier/core/__init__.py
crawlfrontier/tests/__init__.py
crawlfrontier/tests/backends.py
crawlfrontier/settings/default_settings.py
crawlfrontier/settings/__init__.py
crawlfrontier/logger/__init__.py
crawlfrontier/logger/events.py
crawlfrontier/logger/formatters/text.py
crawlfrontier/logger/formatters/color.py
crawlfrontier/logger/formatters/json.py
crawlfrontier/logger/formatters/__init__.py
crawlfrontier/logger/filters/__init__.py
crawlfrontier/logger/handlers/redis.py
crawlfrontier/logger/handlers/__init__.py
crawlfrontier/utils/misc.py
crawlfrontier/utils/tester.py
crawlfrontier/utils/collections.py
crawlfrontier/utils/heap.py
crawlfrontier/utils/fingerprint.py
crawlfrontier/utils/converters.py
crawlfrontier/utils/encoders.py
crawlfrontier/utils/managers.py
crawlfrontier/utils/url.py
crawlfrontier/utils/__init__.py
crawlfrontier/utils/graphs/generate_diagrams.py
crawlfrontier/utils/graphs/data.py
crawlfrontier/utils/graphs/models.py
crawlfrontier/utils/graphs/manager.py
crawlfrontier/utils/graphs/__init__.py
crawlfrontier/contrib/__init__.py
crawlfrontier/contrib/middlewares/fingerprint.py
crawlfrontier/contrib/middlewares/__init__.py
crawlfrontier/contrib/middlewares/domain.py
crawlfrontier/contrib/backends/__init__.py
crawlfrontier/contrib/backends/sqlalchemy.py
crawlfrontier/contrib/backends/memory/test_backend.py
crawlfrontier/contrib/backends/memory/__init__.py
crawlfrontier/contrib/backends/sqlalchemy/test_backend.py
crawlfrontier/contrib/backends/sqlalchemy/__init__.py
crawlfrontier/contrib/requests/converters.py
crawlfrontier/contrib/requests/manager.py
crawlfrontier/contrib/requests/__init__.py
crawlfrontier/contrib/scrapy/converters.py
crawlfrontier/contrib/scrapy/manager.py
crawlfrontier/contrib/scrapy/__init__.py
crawl_frontier-0.2.0.post.dev2.dist-info/WHEEL
crawl_frontier-0.2.0.post.dev2.dist-info/metadata.json
crawl_frontier-0.2.0.post.dev2.dist-info/RECORD
crawl_frontier-0.2.0.post.dev2.dist-info/DESCRIPTION.rst
crawl_frontier-0.2.0.post.dev2.dist-info/METADATA
crawl_frontier-0.2.0.post.dev2.dist-info/top_level.txt
